{"nodes": [{"id": "src_app_app_billing_cancel_page_tsx", "label": "page.tsx", "file_type": "code", "source_file": "src/app/app/billing/cancel/page.tsx", "source_location": "L1"}, {"id": "page_cancelbillingpage", "label": "CancelBillingPage()", "file_type": "code", "source_file": "src/app/app/billing/cancel/page.tsx", "source_location": "L7"}], "edges": [{"source": "src_app_app_billing_cancel_page_tsx", "target": "db", "relation": "imports_from", "confidence": "EXTRACTED", "source_file": "src/app/app/billing/cancel/page.tsx", "source_location": "L1", "weight": 1.0}, {"source": "src_app_app_billing_cancel_page_tsx", "target": "server", "relation": "imports_from", "confidence": "EXTRACTED", "source_file": "src/app/app/billing/cancel/page.tsx", "source_location": "L2", "weight": 1.0}, {"source": "src_app_app_billing_cancel_page_tsx", "target": "multi_org", "relation": "imports_from", "confidence": "EXTRACTED", "source_file": "src/app/app/billing/cancel/page.tsx", "source_location": "L3", "weight": 1.0}, {"source": "src_app_app_billing_cancel_page_tsx", "target": "navigation", "relation": "imports_from", "confidence": "EXTRACTED", "source_file": "src/app/app/billing/cancel/page.tsx", "source_location": "L4", "weight": 1.0}, {"source": "src_app_app_billing_cancel_page_tsx", "target": "src_app_app_billing_cancel_page_client", "relation": "imports_from", "confidence": "EXTRACTED", "source_file": "src/app/app/billing/cancel/page.tsx", "source_location": "L5", "weight": 1.0}, {"source": "src_app_app_billing_cancel_page_tsx", "target": "page_cancelbillingpage", "relation": "contains", "confidence": "EXTRACTED", "source_file": "src/app/app/billing/cancel/page.tsx", "source_location": "L7", "weight": 1.0}]}