{"nodes": [{"id": "src_lib_tests_numbering_test_ts", "label": "numbering.test.ts", "file_type": "code", "source_file": "src/lib/__tests__/numbering.test.ts", "source_location": "L1"}], "edges": [{"source": "src_lib_tests_numbering_test_ts", "target": "vitest", "relation": "imports_from", "confidence": "EXTRACTED", "source_file": "src/lib/__tests__/numbering.test.ts", "source_location": "L1", "weight": 1.0}, {"source": "src_lib_tests_numbering_test_ts", "target": "db", "relation": "imports_from", "confidence": "EXTRACTED", "source_file": "src/lib/__tests__/numbering.test.ts", "source_location": "L14", "weight": 1.0}, {"source": "src_lib_tests_numbering_test_ts", "target": "src_lib_tests_docs_numbering", "relation": "imports_from", "confidence": "EXTRACTED", "source_file": "src/lib/__tests__/numbering.test.ts", "source_location": "L15", "weight": 1.0}]}